[
  {
    "train_number": "465   ",
    "unit_number": "1016.0048",
    "name": "Bischofshofen (in Bo)",
    "abbr": "Bo  ",
    "lat": "47.42",
    "lng": "13.2199",
    "arrival": "2023-08-28T01:36:00Z",
    "departure": "2023-08-28T01:38:00Z"
  },
  {
    "train_number": "465   ",
    "unit_number": "1016.0048",
    "name": "Schwarzach-St.Veit",
    "abbr": "----",
    "lat": "47.3186",
    "lng": "13.1561",
    "arrival": "2023-08-28T01:17:00Z",
    "departure": "2023-08-28T01:24:00Z"
  },
  {
    "train_number": "465   ",
    "unit_number": "1016.0048",
    "name": "Kitzbühel",
    "abbr": "Kzb ",
    "lat": "47.4542",
    "lng": "12.391",
    "arrival": null,
    "departure": "2023-08-28T00:07:00Z"
  },
  {
    "train_number": "465   ",
    "unit_number": "1016.0048",
    "name": "Wörgl Hbf (in W)",
    "abbr": "W   ",
    "lat": "47.4912",
    "lng": "12.0603",
    "arrival": "2023-08-27T23:36:00Z",
    "departure": "2023-08-27T23:38:00Z"
  },
  {
    "train_number": "465   ",
    "unit_number": "1016.0048",
    "name": "Wörgl Hbf-T. N. (in W)",
    "abbr": "Wtn ",
    "lat": "47.4824",
    "lng": "12.033",
    "arrival": null,
    "departure": "2023-08-27T23:33:00Z"
  },
  {
    "train_number": "465   ",
    "unit_number": "1016.0048",
    "name": "Hall in Tirol",
    "abbr": "H   ",
    "lat": "47.2769",
    "lng": "11.5013",
    "arrival": null,
    "departure": "2023-08-27T23:02:00Z"
  },
  {
    "train_number": "465   ",
    "unit_number": "1016.0048",
    "name": "Innsbruck Hbf  (in I)",
    "abbr": "I   ",
    "lat": "47.2634",
    "lng": "11.4017",
    "arrival": "2023-08-27T22:54:00Z",
    "departure": "2023-08-27T22:56:00Z"
  },
  {
    "train_number": "465   ",
    "unit_number": "1016.0048",
    "name": "Imst-Pitztal",
    "abbr": "Im  ",
    "lat": "47.219",
    "lng": "10.7619",
    "arrival": null,
    "departure": "2023-08-27T22:21:00Z"
  },
  {
    "train_number": "465   ",
    "unit_number": "1016.0048",
    "name": "Landeck-Zams",
    "abbr": "Le  ",
    "lat": "47.148",
    "lng": "10.5782",
    "arrival": "2023-08-27T22:07:00Z",
    "departure": "2023-08-27T22:09:00Z"
  },
  {
    "train_number": "465   ",
    "unit_number": "1016.0048",
    "name": "Bludenz",
    "abbr": "B   ",
    "lat": "47.155",
    "lng": "9.81448",
    "arrival": "2023-08-27T20:58:00Z",
    "departure": "2023-08-27T21:01:00Z"
  },
  {
    "train_number": "465   ",
    "unit_number": "1016.0048",
    "name": "Feldkirch",
    "abbr": "Fk  ",
    "lat": "47.2417",
    "lng": "9.60519",
    "arrival": "2023-08-27T20:20:00Z",
    "departure": "2023-08-27T20:45:00Z"
  },
  {
    "train_number": "464   ",
    "unit_number": "1016.0048",
    "name": "Buchs (SG)",
    "abbr": "Bc  ",
    "lat": "47.171",
    "lng": "9.4779",
    "arrival": "2023-08-27T05:54:00Z",
    "departure": "2023-08-27T20:05:00Z"
  },
  {
    "train_number": "464   ",
    "unit_number": "1016.0048",
    "name": "Feldkirch",
    "abbr": "Fk  ",
    "lat": "47.2417",
    "lng": "9.60519",
    "arrival": "2023-08-27T05:21:00Z",
    "departure": "2023-08-27T05:39:00Z"
  },
  {
    "train_number": "464   ",
    "unit_number": "1016.0048",
    "name": "Bludenz",
    "abbr": "B   ",
    "lat": "47.155",
    "lng": "9.81448",
    "arrival": "2023-08-27T04:56:00Z",
    "departure": "2023-08-27T05:06:00Z"
  },
  {
    "train_number": "464   ",
    "unit_number": "1016.0048",
    "name": "Landeck-Zams",
    "abbr": "Le  ",
    "lat": "47.148",
    "lng": "10.5782",
    "arrival": "2023-08-27T03:41:00Z",
    "departure": "2023-08-27T03:45:00Z"
  },
  {
    "train_number": "464   ",
    "unit_number": "1016.0048",
    "name": "Imst-Pitztal",
    "abbr": "Im  ",
    "lat": "47.219",
    "lng": "10.7619",
    "arrival": null,
    "departure": "2023-08-27T03:29:00Z"
  },
  {
    "train_number": "464   ",
    "unit_number": "1016.0048",
    "name": "Innsbruck Hbf  (in I)",
    "abbr": "I   ",
    "lat": "47.2634",
    "lng": "11.4017",
    "arrival": "2023-08-27T02:49:00Z",
    "departure": "2023-08-27T02:53:00Z"
  },
  {
    "train_number": "464   ",
    "unit_number": "1016.0048",
    "name": "Hall in Tirol",
    "abbr": "H   ",
    "lat": "47.2769",
    "lng": "11.5013",
    "arrival": null,
    "departure": "2023-08-27T02:43:00Z"
  }
]
