[
  {
    "train_number": "54581 ",
    "unit_number": "1116.0195",
    "name": "Steindorf b.Straßw. (in Nst)",
    "abbr": "Nst ",
    "lat": "47.9676",
    "lng": "13.2406",
    "arrival": null,
    "departure": "2023-10-23T23:35:00Z"
  },
  {
    "train_number": "54581 ",
    "unit_number": "1116.0195",
    "name": "Attnang-Puchheim",
    "abbr": "At  ",
    "lat": "48.0112",
    "lng": "13.7193",
    "arrival": null,
    "departure": "2023-10-23T22:57:00Z"
  },
  {
    "train_number": "54581 ",
    "unit_number": "1116.0195",
    "name": "Wels Hbf",
    "abbr": "We  ",
    "lat": "48.1662",
    "lng": "14.0273",
    "arrival": null,
    "departure": "2023-10-23T22:32:00Z"
  },
  {
    "train_number": "54581 ",
    "unit_number": "1116.0195",
    "name": "Wels Vbf-Einfgr (in Wev)",
    "abbr": "Wei ",
    "lat": "48.1765",
    "lng": "14.0501",
    "arrival": null,
    "departure": "2023-10-23T22:31:00Z"
  },
  {
    "train_number": null,
    "unit_number": "1116.0195",
    "name": "Wels Vbf (in Wev)",
    "abbr": "Wev ",
    "lat": "48.1834",
    "lng": "14.0628",
    "arrival": null,
    "departure": "2023-10-23T22:30:00Z"
  },
  {
    "train_number": "55896 ",
    "unit_number": "1116.0195",
    "name": "Linz Hbf",
    "abbr": "Lz  ",
    "lat": "48.2908",
    "lng": "14.2927",
    "arrival": null,
    "departure": "2023-10-23T20:15:00Z"
  },
  {
    "train_number": null,
    "unit_number": "1116.0195",
    "name": "Linz Vbf-Ost Reih. (in Lzv)",
    "abbr": "Lo  ",
    "lat": "48.2718",
    "lng": "14.3196",
    "arrival": null,
    "departure": "2023-10-23T20:07:00Z"
  },
  {
    "train_number": "3807  ",
    "unit_number": "1116.0195",
    "name": "Freistadt",
    "abbr": "Fr  ",
    "lat": "48.4952",
    "lng": "14.4815",
    "arrival": "2023-10-23T17:20:00Z",
    "departure": "2023-10-23T17:21:00Z"
  },
  {
    "train_number": "3807  ",
    "unit_number": "1116.0195",
    "name": "Summerau",
    "abbr": "Smr ",
    "lat": "48.5572",
    "lng": "14.4489",
    "arrival": "2023-10-23T17:07:00Z",
    "departure": "2023-10-23T17:12:00Z"
  },
  {
    "train_number": "3804  ",
    "unit_number": "1116.0195",
    "name": "Ceske Budejovice",
    "abbr": "CEBU",
    "lat": "48.9744",
    "lng": "14.4888",
    "arrival": "2023-10-23T13:58:00Z",
    "departure": "2023-10-23T16:03:00Z"
  },
  {
    "train_number": "3804  ",
    "unit_number": "1116.0195",
    "name": "Summerau",
    "abbr": "Smr ",
    "lat": "48.5572",
    "lng": "14.4489",
    "arrival": "2023-10-23T12:47:00Z",
    "departure": "2023-10-23T12:51:00Z"
  },
  {
    "train_number": "3804  ",
    "unit_number": "1116.0195",
    "name": "Freistadt",
    "abbr": "Fr  ",
    "lat": "48.4952",
    "lng": "14.4815",
    "arrival": "2023-10-23T12:38:00Z",
    "departure": "2023-10-23T12:39:00Z"
  },
  {
    "train_number": "3803  ",
    "unit_number": "1116.0195",
    "name": "Linz Hbf",
    "abbr": "Lz  ",
    "lat": "48.2908",
    "lng": "14.2927",
    "arrival": "2023-10-23T10:24:00Z",
    "departure": "2023-10-23T11:35:00Z"
  },
  {
    "train_number": "3803  ",
    "unit_number": "1116.0195",
    "name": "Freistadt",
    "abbr": "Fr  ",
    "lat": "48.4952",
    "lng": "14.4815",
    "arrival": "2023-10-23T09:20:00Z",
    "departure": "2023-10-23T09:21:00Z"
  },
  {
    "train_number": "3803  ",
    "unit_number": "1116.0195",
    "name": "Summerau",
    "abbr": "Smr ",
    "lat": "48.5572",
    "lng": "14.4489",
    "arrival": "2023-10-23T09:07:00Z",
    "departure": "2023-10-23T09:12:00Z"
  },
  {
    "train_number": "3800  ",
    "unit_number": "1116.0195",
    "name": "Ceske Budejovice",
    "abbr": "CEBU",
    "lat": "48.9744",
    "lng": "14.4888",
    "arrival": "2023-10-23T07:58:00Z",
    "departure": "2023-10-23T08:03:00Z"
  },
  {
    "train_number": "3800  ",
    "unit_number": "1116.0195",
    "name": "Summerau",
    "abbr": "Smr ",
    "lat": "48.5572",
    "lng": "14.4489",
    "arrival": "2023-10-23T06:47:00Z",
    "departure": "2023-10-23T06:52:00Z"
  },
  {
    "train_number": "3800  ",
    "unit_number": "1116.0195",
    "name": "Freistadt",
    "abbr": "Fr  ",
    "lat": "48.4952",
    "lng": "14.4815",
    "arrival": "2023-10-23T06:38:00Z",
    "departure": "2023-10-23T06:39:00Z"
  },
  {
    "train_number": "3839  ",
    "unit_number": "1116.0195",
    "name": "Linz Hbf",
    "abbr": "Lz  ",
    "lat": "48.2908",
    "lng": "14.2927",
    "arrival": "2023-10-23T04:51:00Z",
    "departure": "2023-10-23T05:35:00Z"
  },
  {
    "train_number": null,
    "unit_number": "1116.0195",
    "name": "Linz Hbf",
    "abbr": "Lz  ",
    "lat": "48.2908",
    "lng": "14.2927",
    "arrival": null,
    "departure": "2023-10-23T04:09:00Z"
  }
]
