[
  {
    "train_number": "47859 ",
    "unit_number": "1116.0199",
    "name": "Ybbs a.d.Donau",
    "abbr": "Y   ",
    "lat": "48.158",
    "lng": "15.0981",
    "arrival": null,
    "departure": "2023-10-06T23:17:00Z"
  },
  {
    "train_number": "47859 ",
    "unit_number": "1116.0199",
    "name": "Amstetten (in Ams)",
    "abbr": "Ams ",
    "lat": "48.1215",
    "lng": "14.8792",
    "arrival": null,
    "departure": "2023-10-06T23:05:00Z"
  },
  {
    "train_number": "47859 ",
    "unit_number": "1116.0199",
    "name": "St.Valentin (in Sv)",
    "abbr": "Sv  ",
    "lat": "48.1784",
    "lng": "14.5219",
    "arrival": null,
    "departure": "2023-10-06T22:38:00Z"
  },
  {
    "train_number": "47859 ",
    "unit_number": "1116.0199",
    "name": "Linz Hbf",
    "abbr": "Lz  ",
    "lat": "48.2908",
    "lng": "14.2927",
    "arrival": null,
    "departure": "2023-10-06T22:19:00Z"
  },
  {
    "train_number": null,
    "unit_number": "1116.0199",
    "name": "Wels Hbf",
    "abbr": "We  ",
    "lat": "48.1662",
    "lng": "14.0273",
    "arrival": null,
    "departure": "2023-10-06T22:00:00Z"
  },
  {
    "train_number": "55896 ",
    "unit_number": "1116.0199",
    "name": "Linz Hbf",
    "abbr": "Lz  ",
    "lat": "48.2908",
    "lng": "14.2927",
    "arrival": null,
    "departure": "2023-10-06T20:15:00Z"
  },
  {
    "train_number": null,
    "unit_number": "1116.0199",
    "name": "Linz Vbf-Ost Reih. (in Lzv)",
    "abbr": "Lo  ",
    "lat": "48.2718",
    "lng": "14.3196",
    "arrival": null,
    "departure": "2023-10-06T20:07:00Z"
  },
  {
    "train_number": "3807  ",
    "unit_number": "1116.0199",
    "name": "Freistadt",
    "abbr": "Fr  ",
    "lat": "48.4952",
    "lng": "14.4815",
    "arrival": "2023-10-06T17:20:00Z",
    "departure": "2023-10-06T17:21:00Z"
  },
  {
    "train_number": "3807  ",
    "unit_number": "1116.0199",
    "name": "Summerau",
    "abbr": "Smr ",
    "lat": "48.5572",
    "lng": "14.4489",
    "arrival": "2023-10-06T17:07:00Z",
    "departure": "2023-10-06T17:12:00Z"
  },
  {
    "train_number": "3804  ",
    "unit_number": "1116.0199",
    "name": "Ceske Budejovice",
    "abbr": "CEBU",
    "lat": "48.9744",
    "lng": "14.4888",
    "arrival": "2023-10-06T13:58:00Z",
    "departure": "2023-10-06T16:03:00Z"
  },
  {
    "train_number": "3804  ",
    "unit_number": "1116.0199",
    "name": "Summerau",
    "abbr": "Smr ",
    "lat": "48.5572",
    "lng": "14.4489",
    "arrival": "2023-10-06T12:47:00Z",
    "departure": "2023-10-06T12:51:00Z"
  },
  {
    "train_number": "3804  ",
    "unit_number": "1116.0199",
    "name": "Freistadt",
    "abbr": "Fr  ",
    "lat": "48.4952",
    "lng": "14.4815",
    "arrival": "2023-10-06T12:38:00Z",
    "departure": "2023-10-06T12:39:00Z"
  },
  {
    "train_number": "3803  ",
    "unit_number": "1116.0199",
    "name": "Linz Hbf",
    "abbr": "Lz  ",
    "lat": "48.2908",
    "lng": "14.2927",
    "arrival": "2023-10-06T10:24:00Z",
    "departure": "2023-10-06T11:35:00Z"
  },
  {
    "train_number": "3803  ",
    "unit_number": "1116.0199",
    "name": "Freistadt",
    "abbr": "Fr  ",
    "lat": "48.4952",
    "lng": "14.4815",
    "arrival": "2023-10-06T09:20:00Z",
    "departure": "2023-10-06T09:21:00Z"
  },
  {
    "train_number": "3803  ",
    "unit_number": "1116.0199",
    "name": "Summerau",
    "abbr": "Smr ",
    "lat": "48.5572",
    "lng": "14.4489",
    "arrival": "2023-10-06T09:07:00Z",
    "departure": "2023-10-06T09:12:00Z"
  },
  {
    "train_number": "3800  ",
    "unit_number": "1116.0199",
    "name": "Ceske Budejovice",
    "abbr": "CEBU",
    "lat": "48.9744",
    "lng": "14.4888",
    "arrival": "2023-10-06T07:58:00Z",
    "departure": "2023-10-06T08:03:00Z"
  },
  {
    "train_number": "3800  ",
    "unit_number": "1116.0199",
    "name": "Summerau",
    "abbr": "Smr ",
    "lat": "48.5572",
    "lng": "14.4489",
    "arrival": "2023-10-06T06:47:00Z",
    "departure": "2023-10-06T06:52:00Z"
  },
  {
    "train_number": "3800  ",
    "unit_number": "1116.0199",
    "name": "Freistadt",
    "abbr": "Fr  ",
    "lat": "48.4952",
    "lng": "14.4815",
    "arrival": "2023-10-06T06:38:00Z",
    "departure": "2023-10-06T06:39:00Z"
  },
  {
    "train_number": "3839  ",
    "unit_number": "1116.0199",
    "name": "Linz Hbf",
    "abbr": "Lz  ",
    "lat": "48.2908",
    "lng": "14.2927",
    "arrival": "2023-10-06T04:51:00Z",
    "departure": "2023-10-06T05:35:00Z"
  },
  {
    "train_number": null,
    "unit_number": "1116.0199",
    "name": "Linz Hbf",
    "abbr": "Lz  ",
    "lat": "48.2908",
    "lng": "14.2927",
    "arrival": null,
    "departure": "2023-10-06T04:09:00Z"
  }
]
