[
  {
    "train_number": "541   ",
    "unit_number": "8090.0744",
    "name": "Salzburg Hbf (in Sb)",
    "abbr": "Sb  ",
    "lat": "47.8135",
    "lng": "13.0466",
    "arrival": "2023-10-03T20:49:00Z",
    "departure": "2023-10-04T03:11:00Z"
  },
  {
    "train_number": "2602  ",
    "unit_number": "4124.0014",
    "name": "Neusiedl am See",
    "abbr": "Ns  ",
    "lat": "47.9558",
    "lng": "16.8235",
    "arrival": "2023-10-04T02:57:00Z",
    "departure": "2023-10-04T03:01:00Z"
  },
  {
    "train_number": "7906  ",
    "unit_number": "4124.0013",
    "name": "Fertöszentmiklos",
    "abbr": "EM  ",
    "lat": "47.6014",
    "lng": "16.8599",
    "arrival": "2023-10-03T18:50:00Z",
    "departure": "2023-10-04T03:07:00Z"
  },
  {
    "train_number": "84446 ",
    "unit_number": "4024.0130",
    "name": "W. FJBf-Gürtelbrücke (in Wf)",
    "abbr": "Wfg ",
    "lat": "48.227",
    "lng": "16.3611",
    "arrival": "2023-10-03T22:53:00Z",
    "departure": "2023-10-04T02:42:00Z"
  },
  {
    "train_number": "5290  ",
    "unit_number": "4024.0120",
    "name": "Bischofshofen (in Bo)",
    "abbr": "Bo  ",
    "lat": "47.42",
    "lng": "13.2199",
    "arrival": "2023-10-03T23:22:00Z",
    "departure": "2023-10-04T04:24:00Z"
  },
  {
    "train_number": "5005  ",
    "unit_number": "4024.0118",
    "name": "Wörgl Hbf (in W)",
    "abbr": "W   ",
    "lat": "47.4912",
    "lng": "12.0603",
    "arrival": "2023-10-03T19:40:00Z",
    "departure": "2023-10-04T04:05:00Z"
  },
  {
    "train_number": "1734  ",
    "unit_number": "4024.0113",
    "name": "Villach Hbf",
    "abbr": "Vb  ",
    "lat": "46.6186",
    "lng": "13.8484",
    "arrival": "2023-10-04T04:56:00Z",
    "departure": "2023-10-04T04:59:00Z"
  },
  {
    "train_number": "21015 ",
    "unit_number": "4024.0103",
    "name": "St.Pölten Hbf (in Pb)",
    "abbr": "Pb  ",
    "lat": "48.2081",
    "lng": "15.6237",
    "arrival": "2023-10-03T17:44:00Z",
    "departure": "2023-10-04T04:12:00Z"
  },
  {
    "train_number": "85151 ",
    "unit_number": "4024.0089",
    "name": "Wien Westbf (in Ws)",
    "abbr": "Ws  ",
    "lat": "48.1964",
    "lng": "16.3374",
    "arrival": "2023-10-03T17:56:00Z",
    "departure": "2023-10-04T03:56:00Z"
  },
  {
    "train_number": "5010  ",
    "unit_number": "4024.0085",
    "name": "Kitzbühel",
    "abbr": "Kzb ",
    "lat": "47.4542",
    "lng": "12.391",
    "arrival": "2023-10-04T04:20:00Z",
    "departure": "2023-10-04T04:21:00Z"
  },
  {
    "train_number": "5907  ",
    "unit_number": "4024.0016",
    "name": "Schärding (in Sch)",
    "abbr": "Sch ",
    "lat": "48.4638",
    "lng": "13.4424",
    "arrival": "2023-10-03T17:17:00Z",
    "departure": "2023-10-04T03:52:00Z"
  },
  {
    "train_number": "3827  ",
    "unit_number": "4024.0015",
    "name": "Summerau",
    "abbr": "Smr ",
    "lat": "48.5572",
    "lng": "14.4489",
    "arrival": "2023-10-03T18:47:00Z",
    "departure": "2023-10-04T03:32:00Z"
  },
  {
    "train_number": "3929  ",
    "unit_number": "4024.0014",
    "name": "Linz Hbf",
    "abbr": "Lz  ",
    "lat": "48.2908",
    "lng": "14.2927",
    "arrival": "2023-10-04T04:17:00Z",
    "departure": "2023-10-04T04:36:00Z"
  },
  {
    "train_number": "5903  ",
    "unit_number": "4024.0013",
    "name": "Schärding (in Sch)",
    "abbr": "Sch ",
    "lat": "48.4638",
    "lng": "13.4424",
    "arrival": "2023-10-03T17:10:00Z",
    "departure": "2023-10-04T02:32:00Z"
  },
  {
    "train_number": "47802 ",
    "unit_number": "1293.0200",
    "name": "Attnang-Puchheim",
    "abbr": "At  ",
    "lat": "48.0112",
    "lng": "13.7193",
    "arrival": null,
    "departure": "2023-10-04T02:15:00Z"
  },
  {
    "train_number": "45242 ",
    "unit_number": "1293.0018",
    "name": "Tarvisio Boscoverde",
    "abbr": "Tbv ",
    "lat": "46.5059",
    "lng": "13.6081",
    "arrival": "2023-10-04T10:28:00Z",
    "departure": "2023-10-04T10:55:00Z"
  },
  {
    "train_number": "74    ",
    "unit_number": "1216.0229",
    "name": "Graz Hbf (in G)",
    "abbr": "G   ",
    "lat": "47.0733",
    "lng": "15.4163",
    "arrival": "2023-10-03T21:34:00Z",
    "departure": "2023-10-04T06:25:00Z"
  },
  {
    "train_number": "45440 ",
    "unit_number": "1216.0141",
    "name": "Rosenbach",
    "abbr": "Rn  ",
    "lat": "46.5309",
    "lng": "14.0354",
    "arrival": null,
    "departure": "2023-10-04T04:17:00Z"
  },
  {
    "train_number": "83    ",
    "unit_number": "1216.0025",
    "name": "München Hauptbahnhof",
    "abbr": "MH  ",
    "lat": "48.1399",
    "lng": "11.5604",
    "arrival": "2023-10-03T18:26:00Z",
    "departure": "2023-10-04T07:34:00Z"
  },
  {
    "train_number": "86    ",
    "unit_number": "1216.0022",
    "name": "Brennero/Brenner",
    "abbr": "Be  ",
    "lat": "47.0022",
    "lng": "11.5053",
    "arrival": "2023-10-04T11:48:00Z",
    "departure": "2023-10-04T12:00:00Z"
  },
  {
    "train_number": "133   ",
    "unit_number": "1216.0020",
    "name": "Wien Hauptbahnhof (in Wbf)",
    "abbr": "Wbf ",
    "lat": "48.1747",
    "lng": "16.3348",
    "arrival": null,
    "departure": "2023-10-04T10:18:00Z"
  },
  {
    "train_number": "131   ",
    "unit_number": "1216.0019",
    "name": "Wien Hauptbahnhof (in Wbf)",
    "abbr": "Wbf ",
    "lat": "48.1747",
    "lng": "16.3348",
    "arrival": "2023-10-03T21:41:00Z",
    "departure": "2023-10-04T04:18:00Z"
  },
  {
    "train_number": "288   ",
    "unit_number": "1216.0012",
    "name": "Innsbruck Hbf  (in I)",
    "abbr": "I   ",
    "lat": "47.2634",
    "lng": "11.4017",
    "arrival": "2023-10-04T02:38:00Z",
    "departure": "2023-10-04T05:17:00Z"
  },
  {
    "train_number": "166   ",
    "unit_number": "1116.0251",
    "name": "Wien Hauptbahnhof (in Wbf)",
    "abbr": "Wbf ",
    "lat": "48.1747",
    "lng": "16.3348",
    "arrival": null,
    "departure": "2023-10-04T11:28:00Z"
  },
  {
    "train_number": "111   ",
    "unit_number": "1116.0250",
    "name": "München Hauptbahnhof",
    "abbr": "MH  ",
    "lat": "48.1399",
    "lng": "11.5604",
    "arrival": "2023-10-03T19:41:00Z",
    "departure": "2023-10-04T06:18:00Z"
  },
  {
    "train_number": "554   ",
    "unit_number": "1116.0249",
    "name": "Graz Hbf (in G)",
    "abbr": "G   ",
    "lat": "47.0733",
    "lng": "15.4163",
    "arrival": "2023-10-03T18:34:00Z",
    "departure": "2023-10-04T05:25:00Z"
  },
  {
    "train_number": "668   ",
    "unit_number": "1116.0232",
    "name": "Linz Hbf",
    "abbr": "Lz  ",
    "lat": "48.2908",
    "lng": "14.2927",
    "arrival": "2023-10-03T21:30:00Z",
    "departure": "2023-10-04T03:30:00Z"
  },
  {
    "train_number": "1298  ",
    "unit_number": "1116.0229",
    "name": "Salzburg Hbf (in Sb)",
    "abbr": "Sb  ",
    "lat": "47.8135",
    "lng": "13.0466",
    "arrival": "2023-10-03T19:00:00Z",
    "departure": "2023-10-04T04:42:00Z"
  },
  {
    "train_number": "897   ",
    "unit_number": "1116.0225",
    "name": "Lindau-Reutin (in Lir)",
    "abbr": "Lir ",
    "lat": "47.5525",
    "lng": "9.70313",
    "arrival": "2023-10-04T08:28:00Z",
    "departure": "2023-10-04T08:31:00Z"
  },
  {
    "train_number": "260   ",
    "unit_number": "1116.0222",
    "name": "Wien Hauptbahnhof (in Wbf)",
    "abbr": "Wbf ",
    "lat": "48.1747",
    "lng": "16.3348",
    "arrival": null,
    "departure": "2023-10-04T04:28:00Z"
  },
  {
    "train_number": "56900 ",
    "unit_number": "1116.0200",
    "name": "Pöchlarn",
    "abbr": "Poe ",
    "lat": "48.208",
    "lng": "15.2148",
    "arrival": null,
    "departure": "2023-10-04T03:04:00Z"
  },
  {
    "train_number": "48402 ",
    "unit_number": "1116.0199",
    "name": "St.Valentin (in Sv)",
    "abbr": "Sv  ",
    "lat": "48.1784",
    "lng": "14.5219",
    "arrival": null,
    "departure": "2023-10-04T02:39:00Z"
  },
  {
    "train_number": "2215  ",
    "unit_number": "1116.0195",
    "name": "Retz",
    "abbr": "R   ",
    "lat": "48.7539",
    "lng": "15.9574",
    "arrival": "2023-10-04T01:32:00Z",
    "departure": "2023-10-04T04:36:00Z"
  },
  {
    "train_number": "79550 ",
    "unit_number": "1116.0182",
    "name": "Hohenau",
    "abbr": "Nh  ",
    "lat": "48.5981",
    "lng": "16.9008",
    "arrival": "2023-10-03T21:11:00Z",
    "departure": "2023-10-04T02:30:00Z"
  },
  {
    "train_number": "84576 ",
    "unit_number": "1116.0181",
    "name": "Hohenau",
    "abbr": "Nh  ",
    "lat": "48.5981",
    "lng": "16.9008",
    "arrival": "2023-10-04T03:00:00Z",
    "departure": "2023-10-04T03:10:00Z"
  },
  {
    "train_number": "54685 ",
    "unit_number": "1116.0168",
    "name": "Selzthal (in Sl)",
    "abbr": "Sl  ",
    "lat": "47.5505",
    "lng": "14.3134",
    "arrival": "2023-10-04T02:09:00Z",
    "departure": "2023-10-04T04:52:00Z"
  },
  {
    "train_number": "541   ",
    "unit_number": "1116.0165",
    "name": "Salzburg Hbf (in Sb)",
    "abbr": "Sb  ",
    "lat": "47.8135",
    "lng": "13.0466",
    "arrival": "2023-10-03T20:49:00Z",
    "departure": "2023-10-04T03:11:00Z"
  },
  {
    "train_number": "88411 ",
    "unit_number": "1116.0159",
    "name": "Innsbruck Hbf  (in I)",
    "abbr": "I   ",
    "lat": "47.2634",
    "lng": "11.4017",
    "arrival": "2023-10-04T00:54:00Z",
    "departure": "2023-10-04T03:43:00Z"
  },
  {
    "train_number": "2211  ",
    "unit_number": "1116.0157",
    "name": "Retz",
    "abbr": "R   ",
    "lat": "48.7539",
    "lng": "15.9574",
    "arrival": "2023-10-04T03:20:00Z",
    "departure": "2023-10-04T03:30:00Z"
  },
  {
    "train_number": "691   ",
    "unit_number": "1116.0153",
    "name": "Klagenfurt Hbf (in Kt)",
    "abbr": "Kt  ",
    "lat": "46.6156",
    "lng": "14.3137",
    "arrival": "2023-10-03T19:16:00Z",
    "departure": "2023-10-04T04:45:00Z"
  },
  {
    "train_number": "515   ",
    "unit_number": "1116.0143",
    "name": "Innsbruck Hbf  (in I)",
    "abbr": "I   ",
    "lat": "47.2634",
    "lng": "11.4017",
    "arrival": null,
    "departure": "2023-10-04T06:21:00Z"
  },
  {
    "train_number": "29468 ",
    "unit_number": "1116.0072",
    "name": "Hegyeshalom",
    "abbr": "He  ",
    "lat": "47.9139",
    "lng": "17.1455",
    "arrival": "2023-10-03T19:11:00Z",
    "departure": "2023-10-04T04:00:00Z"
  },
  {
    "train_number": "63024 ",
    "unit_number": "1116.0016",
    "name": "Tulln a. d. Donau (in Tu)",
    "abbr": "Tu  ",
    "lat": "48.3275",
    "lng": "16.0644",
    "arrival": null,
    "departure": "2023-10-04T03:02:00Z"
  },
  {
    "train_number": "74699 ",
    "unit_number": "1063.0039",
    "name": "Bruck a.d.Mur (in Bm)",
    "abbr": "Bm  ",
    "lat": "47.4134",
    "lng": "15.2797",
    "arrival": "2023-10-04T01:59:00Z",
    "departure": "2023-10-04T02:19:00Z"
  },
  {
    "train_number": "74697 ",
    "unit_number": "1063.0039",
    "name": "Bruck a.d.Mur (in Bm)",
    "abbr": "Bm  ",
    "lat": "47.4134",
    "lng": "15.2797",
    "arrival": "2023-10-04T01:59:00Z",
    "departure": "2023-10-04T02:19:00Z"
  },
  {
    "train_number": "86622 ",
    "unit_number": "1016.0023",
    "name": "Wien Zvbf-Einfgr. (in Zur)",
    "abbr": "Ze  ",
    "lat": "48.1453",
    "lng": "16.43",
    "arrival": "2023-10-04T00:47:00Z",
    "departure": "2023-10-04T02:44:00Z"
  },
  {
    "train_number": "63028 ",
    "unit_number": "1016.0021",
    "name": "Wien Zvbf (in Zur)",
    "abbr": "Zur ",
    "lat": "48.1453",
    "lng": "16.43",
    "arrival": null,
    "departure": "2023-10-04T06:06:00Z"
  },
  {
    "train_number": "86652 ",
    "unit_number": "1016.0020",
    "name": "Wien Zvbf-Einfgr. (in Zur)",
    "abbr": "Ze  ",
    "lat": "48.1453",
    "lng": "16.43",
    "arrival": "2023-10-03T20:38:00Z",
    "departure": "2023-10-04T02:19:00Z"
  }
]
