[
  {
    "train_number": "539   ",
    "unit_number": "8090.0744",
    "name": "Wien Hauptbahnhof (in Wbf)",
    "abbr": "Wbf ",
    "lat": "48.1747",
    "lng": "16.3348",
    "arrival": "2023-09-14T11:42:00Z",
    "departure": "2023-09-14T12:18:00Z"
  },
  {
    "train_number": "84930 ",
    "unit_number": "5047.0085",
    "name": "Wels Hbf",
    "abbr": "We  ",
    "lat": "48.1662",
    "lng": "14.0273",
    "arrival": "2023-09-14T02:38:00Z",
    "departure": "2023-09-14T03:42:00Z"
  },
  {
    "train_number": "7905  ",
    "unit_number": "4124.0014",
    "name": "Neusiedl am See",
    "abbr": "Ns  ",
    "lat": "47.9558",
    "lng": "16.8235",
    "arrival": "2023-09-14T03:28:00Z",
    "departure": "2023-09-14T03:33:00Z"
  },
  {
    "train_number": "84309 ",
    "unit_number": "4124.0013",
    "name": "Wien Hbf Autoreis. (in Wbf)",
    "abbr": "Of  ",
    "lat": "48.1747",
    "lng": "16.3348",
    "arrival": null,
    "departure": "2023-09-14T04:09:00Z"
  },
  {
    "train_number": "5140  ",
    "unit_number": "4024.0120",
    "name": "Innsbruck Hbf  (in I)",
    "abbr": "I   ",
    "lat": "47.2634",
    "lng": "11.4017",
    "arrival": "2023-09-13T22:53:00Z",
    "departure": "2023-09-14T02:59:00Z"
  },
  {
    "train_number": "5007  ",
    "unit_number": "4024.0118",
    "name": "Wörgl Hbf (in W)",
    "abbr": "W   ",
    "lat": "47.4912",
    "lng": "12.0603",
    "arrival": "2023-09-13T23:03:00Z",
    "departure": "2023-09-14T04:34:00Z"
  },
  {
    "train_number": "1734  ",
    "unit_number": "4024.0113",
    "name": "Villach Hbf",
    "abbr": "Vb  ",
    "lat": "46.6186",
    "lng": "13.8484",
    "arrival": "2023-09-14T04:56:00Z",
    "departure": "2023-09-14T04:59:00Z"
  },
  {
    "train_number": "21090 ",
    "unit_number": "4024.0103",
    "name": "Tulln a. d. Donau (in Tu)",
    "abbr": "Tu  ",
    "lat": "48.3275",
    "lng": "16.0644",
    "arrival": "2023-09-13T22:32:00Z",
    "departure": "2023-09-14T02:41:00Z"
  },
  {
    "train_number": "21022 ",
    "unit_number": "4024.0089",
    "name": "Wien FJBf (in Wf)",
    "abbr": "Wf  ",
    "lat": "48.227",
    "lng": "16.3611",
    "arrival": "2023-09-13T18:51:00Z",
    "departure": "2023-09-14T08:39:00Z"
  },
  {
    "train_number": "5404  ",
    "unit_number": "4024.0088",
    "name": "Innsbruck Hbf  (in I)",
    "abbr": "I   ",
    "lat": "47.2634",
    "lng": "11.4017",
    "arrival": "2023-09-14T04:30:00Z",
    "departure": "2023-09-14T04:38:00Z"
  },
  {
    "train_number": "5201  ",
    "unit_number": "4024.0085",
    "name": "Brennero/Brenner",
    "abbr": "Be  ",
    "lat": "47.0022",
    "lng": "11.5053",
    "arrival": "2023-09-13T22:44:00Z",
    "departure": "2023-09-14T03:27:00Z"
  },
  {
    "train_number": "5933  ",
    "unit_number": "4024.0016",
    "name": "Passau Hbf",
    "abbr": "Pa  ",
    "lat": "48.5729",
    "lng": "13.4342",
    "arrival": "2023-09-14T05:27:00Z",
    "departure": "2023-09-14T05:40:00Z"
  },
  {
    "train_number": "5051  ",
    "unit_number": "4024.0015",
    "name": "Freilassing",
    "abbr": "MFL ",
    "lat": "47.8368",
    "lng": "12.9764",
    "arrival": "2023-09-13T19:43:00Z",
    "departure": "2023-09-14T03:17:00Z"
  },
  {
    "train_number": "3409  ",
    "unit_number": "4024.0014",
    "name": "Stainach-Irdning",
    "abbr": "Rg  ",
    "lat": "47.5293",
    "lng": "14.1078",
    "arrival": "2023-09-14T03:37:00Z",
    "departure": "2023-09-14T04:09:00Z"
  },
  {
    "train_number": "84771 ",
    "unit_number": "4024.0013",
    "name": "Linz Hbf",
    "abbr": "Lz  ",
    "lat": "48.2908",
    "lng": "14.2927",
    "arrival": "2023-09-14T03:24:00Z",
    "departure": "2023-09-14T03:28:00Z"
  },
  {
    "train_number": "49405 ",
    "unit_number": "1293.0200",
    "name": "Hohenau",
    "abbr": "Nh  ",
    "lat": "48.5981",
    "lng": "16.9008",
    "arrival": "2023-09-14T02:52:00Z",
    "departure": "2023-09-14T03:24:00Z"
  },
  {
    "train_number": "45152 ",
    "unit_number": "1293.0018",
    "name": "Brennero/Brenner",
    "abbr": "Be  ",
    "lat": "47.0022",
    "lng": "11.5053",
    "arrival": "2023-09-14T08:17:00Z",
    "departure": "2023-09-14T08:48:00Z"
  },
  {
    "train_number": "41170 ",
    "unit_number": "1293.0012",
    "name": "Parndorf",
    "abbr": "Par ",
    "lat": "47.987",
    "lng": "16.8702",
    "arrival": null,
    "departure": "2023-09-14T02:51:00Z"
  },
  {
    "train_number": "533   ",
    "unit_number": "1216.0229",
    "name": "Wien Hauptbahnhof (in Wbf)",
    "abbr": "Wbf ",
    "lat": "48.1747",
    "lng": "16.3348",
    "arrival": "2023-09-12T19:42:00Z",
    "departure": "2023-09-14T06:18:00Z"
  },
  {
    "train_number": "576   ",
    "unit_number": "1216.0210",
    "name": "Brno Hlavni Nadrazi",
    "abbr": "BRHN",
    "lat": "49.1909",
    "lng": "16.6134",
    "arrival": "2023-09-13T20:36:00Z",
    "departure": "2023-09-14T02:39:00Z"
  },
  {
    "train_number": "212   ",
    "unit_number": "1216.0141",
    "name": "Dobova",
    "abbr": "DO  ",
    "lat": "45.8977",
    "lng": "15.6597",
    "arrival": "2023-09-13T18:08:00Z",
    "departure": "2023-09-14T05:45:00Z"
  },
  {
    "train_number": "85904 ",
    "unit_number": "1216.0020",
    "name": "Wien Westbf (in Ws)",
    "abbr": "Ws  ",
    "lat": "48.1964",
    "lng": "16.3374",
    "arrival": "2023-09-13T04:12:00Z",
    "departure": "2023-09-14T05:34:00Z"
  },
  {
    "train_number": "132   ",
    "unit_number": "1216.0019",
    "name": "Tarvisio Boscoverde",
    "abbr": "Tbv ",
    "lat": "46.5059",
    "lng": "13.6081",
    "arrival": "2023-09-14T10:41:00Z",
    "departure": "2023-09-14T10:49:00Z"
  },
  {
    "train_number": "5344  ",
    "unit_number": "1216.0012",
    "name": "Kufstein",
    "abbr": "K   ",
    "lat": "47.5833",
    "lng": "12.1657",
    "arrival": "2023-09-13T15:48:00Z",
    "departure": "2023-09-14T04:29:00Z"
  },
  {
    "train_number": "41401 ",
    "unit_number": "1116.0276",
    "name": "Graz Vbf (in G)",
    "abbr": "Gi  ",
    "lat": "47.0885",
    "lng": "15.4077",
    "arrival": "2023-09-14T03:16:00Z",
    "departure": "2023-09-14T03:25:00Z"
  },
  {
    "train_number": "85510 ",
    "unit_number": "1116.0251",
    "name": "Wolfurt (in Wo)",
    "abbr": "Wo  ",
    "lat": "47.457",
    "lng": "9.74133",
    "arrival": "2023-09-13T17:41:00Z",
    "departure": "2023-09-14T05:55:00Z"
  },
  {
    "train_number": "545   ",
    "unit_number": "1116.0250",
    "name": "Salzburg Hbf (in Sb)",
    "abbr": "Sb  ",
    "lat": "47.8135",
    "lng": "13.0466",
    "arrival": "2023-09-14T04:19:00Z",
    "departure": "2023-09-14T05:11:00Z"
  },
  {
    "train_number": "669   ",
    "unit_number": "1116.0249",
    "name": "Innsbruck Hbf  (in I)",
    "abbr": "I   ",
    "lat": "47.2634",
    "lng": "11.4017",
    "arrival": "2023-09-13T21:48:00Z",
    "departure": "2023-09-14T03:10:00Z"
  },
  {
    "train_number": "539   ",
    "unit_number": "1116.0244",
    "name": "Wien Hauptbahnhof (in Wbf)",
    "abbr": "Wbf ",
    "lat": "48.1747",
    "lng": "16.3348",
    "arrival": "2023-09-14T11:42:00Z",
    "departure": "2023-09-15T12:18:00Z"
  },
  {
    "train_number": "530   ",
    "unit_number": "1116.0232",
    "name": "Villach Hbf",
    "abbr": "Vb  ",
    "lat": "46.6186",
    "lng": "13.8484",
    "arrival": "2023-09-13T18:46:00Z",
    "departure": "2023-09-14T03:25:00Z"
  },
  {
    "train_number": "47306 ",
    "unit_number": "1116.0231",
    "name": "Hegyeshalom",
    "abbr": "He  ",
    "lat": "47.9139",
    "lng": "17.1455",
    "arrival": "2023-09-13T22:42:00Z",
    "departure": "2023-09-14T02:40:00Z"
  },
  {
    "train_number": "162   ",
    "unit_number": "1116.0229",
    "name": "Budapest Keleti",
    "abbr": "BPK ",
    "lat": "47.501",
    "lng": "19.0869",
    "arrival": "2023-09-13T22:19:00Z",
    "departure": "2023-09-14T04:40:00Z"
  },
  {
    "train_number": "18096 ",
    "unit_number": "1116.0200",
    "name": "Amstetten (in Ams)",
    "abbr": "Ams ",
    "lat": "48.1215",
    "lng": "14.8792",
    "arrival": "2023-09-14T02:00:00Z",
    "departure": "2023-09-14T04:09:00Z"
  },
  {
    "train_number": "3840  ",
    "unit_number": "1116.0199",
    "name": "Linz Hbf",
    "abbr": "Lz  ",
    "lat": "48.2908",
    "lng": "14.2927",
    "arrival": null,
    "departure": "2023-09-14T04:09:00Z"
  },
  {
    "train_number": "88409 ",
    "unit_number": "1116.0195",
    "name": "Innsbruck Hbf  (in I)",
    "abbr": "I   ",
    "lat": "47.2634",
    "lng": "11.4017",
    "arrival": "2023-09-14T01:16:00Z",
    "departure": "2023-09-14T02:50:00Z"
  },
  {
    "train_number": "84323 ",
    "unit_number": "1116.0165",
    "name": "W. Matzleinsdorf (in Wbf)",
    "abbr": "Mat ",
    "lat": "48.1747",
    "lng": "16.3348",
    "arrival": "2023-09-14T12:00:00Z",
    "departure": "2023-09-14T12:23:00Z"
  },
  {
    "train_number": "40627 ",
    "unit_number": "1116.0159",
    "name": "Wels Vbf (in Wev)",
    "abbr": "Wev ",
    "lat": "48.1662",
    "lng": "14.0273",
    "arrival": "2023-09-14T01:36:00Z",
    "departure": "2023-09-14T02:25:00Z"
  },
  {
    "train_number": "45514 ",
    "unit_number": "1116.0158",
    "name": "Schwarzenau",
    "abbr": "Swu ",
    "lat": "48.7464",
    "lng": "15.2673",
    "arrival": "2023-09-14T02:41:00Z",
    "departure": "2023-09-14T04:11:00Z"
  },
  {
    "train_number": "44858 ",
    "unit_number": "1116.0157",
    "name": "Kufstein",
    "abbr": "K   ",
    "lat": "47.5833",
    "lng": "12.1657",
    "arrival": "2023-09-14T02:52:00Z",
    "departure": "2023-09-14T03:23:00Z"
  },
  {
    "train_number": "639   ",
    "unit_number": "1116.0153",
    "name": "Graz Hbf (in G)",
    "abbr": "G   ",
    "lat": "47.0733",
    "lng": "15.4163",
    "arrival": "2023-09-13T18:34:00Z",
    "departure": "2023-09-14T03:19:00Z"
  },
  {
    "train_number": "2190  ",
    "unit_number": "1116.0143",
    "name": "Gmünd N.Ö.",
    "abbr": "Gm  ",
    "lat": "48.7646",
    "lng": "14.985",
    "arrival": "2023-09-14T03:00:00Z",
    "departure": "2023-09-14T03:22:00Z"
  },
  {
    "train_number": "88131 ",
    "unit_number": "1116.0077",
    "name": "Linz Hbf",
    "abbr": "Lz  ",
    "lat": "48.2908",
    "lng": "14.2927",
    "arrival": null,
    "departure": "2023-09-14T10:10:00Z"
  },
  {
    "train_number": "90820 ",
    "unit_number": "1116.0016",
    "name": "Budapest-Ferencvaros",
    "abbr": "BUFE",
    "lat": "47.4687",
    "lng": "19.0882",
    "arrival": null,
    "departure": "2023-09-14T09:00:00Z"
  },
  {
    "train_number": "63028 ",
    "unit_number": "1116.0007",
    "name": "Wien Zvbf (in Zur)",
    "abbr": "Zur ",
    "lat": "48.1453",
    "lng": "16.43",
    "arrival": null,
    "departure": "2023-09-14T06:06:00Z"
  },
  {
    "train_number": "88902 ",
    "unit_number": "1063.0039",
    "name": "Bruck a.d.Mur (in Bm)",
    "abbr": "Bm  ",
    "lat": "47.4134",
    "lng": "15.2797",
    "arrival": null,
    "departure": "2023-09-14T02:27:00Z"
  },
  {
    "train_number": "44990 ",
    "unit_number": "1016.0023",
    "name": "Salzburg Gnigl (in Sb)",
    "abbr": "Srh1",
    "lat": "47.8075",
    "lng": "13.0021",
    "arrival": null,
    "departure": "2023-09-14T06:30:00Z"
  },
  {
    "train_number": "41972 ",
    "unit_number": "1016.0021",
    "name": "Wolfurt (in Wo)",
    "abbr": "Wo  ",
    "lat": "47.457",
    "lng": "9.74133",
    "arrival": "2023-09-13T22:41:00Z",
    "departure": "2023-09-14T06:37:00Z"
  }
]
